docscraper/__init__.py
docscraper/__main__.py
docscraper/api.py
docscraper/items.py
docscraper/middlewares.py
docscraper/pipelines.py
docscraper/settings.py
docscraper/spiders/__init__.py
docscraper/spiders/docscraper.py
tests/__init__.py
tests/base.py
tests/test_api.py
tests/test_spiders_docscraper.py
docscraper-2.0.7.dist-info/METADATA
docscraper-2.0.7.dist-info/WHEEL
docscraper-2.0.7.dist-info/top_level.txt
docscraper-2.0.7.dist-info/RECORD
