Metadata-Version: 2.1
Name: docscraper
Version: 2.0.7
Summary: A web crawler to scrape documents from websites
Home-page: https://docscraper.readthedocs.io/en/latest/
Author: Patrick Ryan
Author-email: pjryan126@gmail.com
License: MIT
Platform: UNKNOWN
Requires-Dist: openpyxl
Requires-Dist: numpy (>=1.16.5)
Requires-Dist: pandas
Requires-Dist: requests
Requires-Dist: scrapy
Requires-Dist: scrapy-wayback-machine
